tarc/__init__.py
tarc/main.py
tarc-0.0.1.dev3.dist-info/METADATA
tarc-0.0.1.dev3.dist-info/WHEEL
tarc-0.0.1.dev3.dist-info/entry_points.txt
tarc-0.0.1.dev3.dist-info/top_level.txt
tarc-0.0.1.dev3.dist-info/RECORD
