Metadata-Version: 2.1
Name: tarc
Version: 0.0.1.dev3
Summary: Manage BT archives
